cartoee/__init__.py
cartoee/core.py
cartoee/plotting.py
cartoee/tests/__init__.py
cartoee/tests/installation_test.py
cartoee/tests/logo.py
cartoee/tests/plotting_test.py
cartoee-0.0.5.dist-info/METADATA
cartoee-0.0.5.dist-info/RECORD
cartoee-0.0.5.dist-info/WHEEL
cartoee-0.0.5.dist-info/entry_points.txt
cartoee-0.0.5.dist-info/top_level.txt
