Metadata-Version: 2.1
Name: cartoee
Version: 0.0.5
Summary: Publication quality maps using Earth Engine and Cartopy!
Home-page: http://github.com/kmarkert/cartoee
Author: Kel Markert
Author-email: kel.markert@gmail.com
License: GNU GPL v3
Platform: UNKNOWN
Requires-Dist: matplotlib
Requires-Dist: Cython
Requires-Dist: geos
Requires-Dist: pyproj
Requires-Dist: cartopy (==0.16.0)
Requires-Dist: oauth2client
Requires-Dist: google-api-python-client
Requires-Dist: earthengine-api
